clickup_pipeline/__init__.py
clickup_pipeline/clickup_pipeline.py
clickup_pipeline-1.0.0.dist-info/METADATA
clickup_pipeline-1.0.0.dist-info/WHEEL
clickup_pipeline-1.0.0.dist-info/RECORD
