Metadata-Version: 2.1
Name: clickup_pipeline
Version: 1.0.0
Summary: A Pipeline for loading data from clickup to Postgres Database
Author: Your Name
Author-email: you@example.com
Requires-Python: >=3.10,<3.13
Classifier: Programming Language :: Python :: 3
Classifier: Programming Language :: Python :: 3.10
Classifier: Programming Language :: Python :: 3.11
Classifier: Programming Language :: Python :: 3.12
Requires-Dist: apache-airflow (==2.9.0rc1)
Requires-Dist: apache-airflow-providers-fab (==1.0.2rc1)
Requires-Dist: attrs (==22.2.0)
Requires-Dist: flask (==2.2.5)
Requires-Dist: pluggy (>=1.0)
Requires-Dist: poetry (==1.8.2)
Requires-Dist: psycopg2-binary (==2.9.9)
Requires-Dist: python-dotenv (==1.0.1)
Requires-Dist: requests (==2.29.0)
